git2text.py
git2text-0.1.dist-info/METADATA
git2text-0.1.dist-info/WHEEL
git2text-0.1.dist-info/entry_points.txt
git2text-0.1.dist-info/top_level.txt
git2text-0.1.dist-info/RECORD
