Metadata-Version: 2.1
Name: git2text
Version: 0.1
Summary: A utility to extract and format a codebase into Markdown format
Home-page: https://github.com/mrauter1/git2text
Author: Marcelo Rauter
Author-email: marcelorauter2@gmail.com
Classifier: Programming Language :: Python :: 3
Classifier: License :: OSI Approved :: MIT License
Classifier: Operating System :: OS Independent
Requires-Python: >=3.6
Requires-Dist: pathspec
